chunkmate/__init__.py
chunkmate/chunkers/__init__.py
chunkmate/chunkers/async_chunker.py
chunkmate/chunkers/base_chunker.py
chunkmate/chunkers/chunk.py
chunkmate/chunkers/chunker.py
chunkmate/metadata/__init__.py
chunkmate/metadata/protocols.py
chunkmate/py.typed
chunkmate/splitters/__init__.py
chunkmate/splitters/html_splitter.py
chunkmate/splitters/json_splitter.py
chunkmate/splitters/markdown_splitter.py
chunkmate/splitters/protocols.py
chunkmate/splitters/text_splitter.py
chunkmate/utils/converters.py
chunkmate/utils/reflection.py
chunkmate/utils/tokens.py
chunkmate-0.1.0.dist-info/WHEEL
chunkmate-0.1.0.dist-info/METADATA
chunkmate-0.1.0.dist-info/RECORD
