Metadata-Version: 2.3
Name: chunkmate
Version: 0.1.0
Summary: Intelligent text and document chunking library with automatic format detection and AI-powered metadata generation for RAG, LLMs, and text processing pipelines
Keywords: text-splitting,chunking,text-processing,langchain,llama-index,rag,semantic-chunking
Author: Giannis Vrentzos
Author-email: Giannis Vrentzos <gvre@gvre.gr>
License: MIT
Requires-Dist: html2text>=2025.4.15
Requires-Dist: langchain-text-splitters>=1.1.0
Requires-Dist: tiktoken>=0.12.0
Requires-Dist: langchain-core>=1.2.5 ; extra == 'all'
Requires-Dist: llama-index-core>=0.14.10 ; extra == 'all'
Requires-Dist: ty>=0.0.4 ; extra == 'dev'
Requires-Dist: pytest>=9.0.2 ; extra == 'dev'
Requires-Dist: pytest-cov>=7.0.0 ; extra == 'dev'
Requires-Dist: pytest-asyncio>=1.3.0 ; extra == 'dev'
Requires-Dist: ruff>=0.14.10 ; extra == 'dev'
Requires-Dist: langchain-core>=1.2.5 ; extra == 'langchain'
Requires-Dist: llama-index-core>=0.14.10 ; extra == 'llamaindex'
Requires-Python: >=3.12
Project-URL: Changelog, https://github.com/gvre/chunkmate/releases
Project-URL: Homepage, https://github.com/gvre/chunkmate
Project-URL: Issues, https://github.com/gvre/chunkmate/issues
Project-URL: Repository, https://github.com/gvre/chunkmate
Provides-Extra: all
Provides-Extra: dev
Provides-Extra: langchain
Provides-Extra: llamaindex
